{
  "permeate": {
    "word": "permeate",
    "partOfSpeech": "Verb",
    "language": "English",
    "definitions": {
      "definition": "To pass through the pores or interstices of; to penetrate and pass through without causing rupture or displacement; applied especially to fluids which pass through substances of loose texture",
      "parsedExamples": [
        {
          "example": "water permeates sand"
        }
      ],
      "examples": [
        "water permeates sand"
      ]
    }
  }
}