{
  "relict": {
    "word": "relict",
    "partOfSpeech": "Noun",
    "language": "English",
    "definitions": {
      "definition": "Something that, or someone who, survives or remains or is left over after the loss of others; a relic.\n The surviving member of a married couple after one or the other has died; a widow or widower.\n\n A species, organism, or ecosystem that has survived from a previous age: one that was once widespread but is now found only in a few areas.\n\n A structure or other feature that has survived from a previous age.\n\n A survival of an archaic word, language or other form.",
      "parsedExamples": [
        {
          "example": "A small number of linguists believe that Cimbrian is not an Austro-Bavarian dialect but a relict of Lombardic."
        }
      ],
      "examples": [
        "A small number of linguists believe that Cimbrian is not an Austro-Bavarian dialect but a relict of Lombardic."
      ]
    }
  }
}